{
  "coverage": {
    "artifacts": {
      "calculations": "partial",
      "dashboards": "full",
      "fields": "full",
      "filters": "full",
      "layout": "full",
      "models": "partial",
      "permissions": "unsupported",
      "relationships": "partial",
      "schedules": "unsupported",
      "tiles": "full",
      "topics": "full",
      "views": "full"
    },
    "fidelity_classes": {
      "full": [
        "dashboards",
        "fields",
        "filters",
        "layout",
        "tiles",
        "topics",
        "views"
      ],
      "partial": [
        "calculations",
        "models",
        "relationships"
      ],
      "unsupported": [
        "permissions",
        "schedules"
      ]
    }
  },
  "objects": {
    "dashboards": [
      {
        "filters": [
          {
            "field": "status",
            "is_negative": false,
            "operator": "default",
            "values": [
              "completed"
            ]
          }
        ],
        "name": "Operations overview",
        "tiles": [
          {
            "chart_type": "column",
            "kind": "query",
            "layout": {
              "h": 4,
              "w": 6,
              "x": 0,
              "y": 0
            },
            "query": {
              "fields": [
                "status",
                "total_revenue"
              ],
              "filters": [
                {
                  "field": "status",
                  "is_negative": false,
                  "operator": "equals",
                  "values": [
                    "completed"
                  ]
                }
              ],
              "limit": null,
              "pivots": [],
              "topic": "orders"
            },
            "title": "Revenue by status"
          }
        ]
      }
    ],
    "topics": [
      {
        "base_view": "orders",
        "joins": [
          {
            "from": "orders",
            "join_type": "always_left",
            "on_sql": "${orders.customer_id} = ${customers.id}",
            "relationship_type": "many_to_one",
            "to": "customers"
          }
        ],
        "name": "orders"
      }
    ],
    "views": [
      {
        "connection": {
          "dialect": "postgres",
          "source_name": "1"
        },
        "derived_sql": null,
        "fields": [
          {
            "aggregate": null,
            "data_type": "number",
            "filters": {},
            "kind": "dimension",
            "name": "id",
            "primary_key": true,
            "sql": "id"
          },
          {
            "aggregate": null,
            "data_type": "string",
            "filters": {},
            "kind": "dimension",
            "name": "name",
            "primary_key": false,
            "sql": "name"
          }
        ],
        "name": "customers",
        "schema": "public",
        "source_table": "customers"
      },
      {
        "connection": {
          "dialect": "postgres",
          "source_name": "1"
        },
        "derived_sql": null,
        "fields": [
          {
            "aggregate": null,
            "data_type": "number",
            "filters": {},
            "kind": "dimension",
            "name": "amount",
            "primary_key": false,
            "sql": "amount"
          },
          {
            "aggregate": null,
            "data_type": "boolean",
            "filters": {},
            "kind": "dimension",
            "name": "completed_orders",
            "primary_key": false,
            "sql": "status = 'completed'"
          },
          {
            "aggregate": null,
            "data_type": "number",
            "filters": {},
            "kind": "dimension",
            "name": "customer_id",
            "primary_key": false,
            "sql": "customer_id"
          },
          {
            "aggregate": null,
            "data_type": "number",
            "filters": {},
            "kind": "dimension",
            "name": "id",
            "primary_key": true,
            "sql": "id"
          },
          {
            "aggregate": null,
            "data_type": "string",
            "filters": {},
            "kind": "dimension",
            "name": "status",
            "primary_key": false,
            "sql": "status"
          },
          {
            "aggregate": "sum",
            "data_type": "number",
            "filters": {},
            "kind": "measure",
            "name": "total_revenue",
            "primary_key": false,
            "sql": "amount"
          }
        ],
        "name": "orders",
        "schema": "public",
        "source_table": "orders"
      }
    ]
  },
  "review": {
    "counts": {
      "blocker": 0,
      "info": 1,
      "warning": 0
    },
    "limitations": [
      "Native SQL cards and unresolved ad-hoc aggregations require review."
    ],
    "objects": [
      "info:join orders.customer_id -> customers.id"
    ]
  },
  "schema_version": "omnikit.migration.conformance.v1",
  "source": "metabase"
}
